LICENSE.txt
setup.py
Kholoud.egg-info/PKG-INFO
Kholoud.egg-info/SOURCES.txt
Kholoud.egg-info/dependency_links.txt
Kholoud.egg-info/top_level.txt
code/__init__.py