Metadata-Version: 2.1
Name: Kholoud
Version: 0.1
Summary: easy calc
Author: Kholoud
License-File: LICENSE.txt
